<scm:Change.list
  xmlns:scm="class:/spiralcraft/scm/meta/"
  >
  <scm:Change>
  
    <revision>0.4.17
    </revision>
    
    <authorId>miketoth
    </authorId>
    
    <date>
    </date>
    
    <detail>
    
      <scm:Change>
        <revision>-dev2
        </revision>
        
        <notes>
          <scm:Note>Handle error/problem callbacks
          </scm:Note>
        </notes>

        <path>package/war-webui/auth.webui
        </path>
        
        <resources>
          <URI>Client.java
          </URI>
          <URI>Scope.java
          </URI>
          <URI>StandardClient.assy.xml
          </URI>
        </resources>
      </scm:Change>

      <scm:Change>
        <revision>-dev2
        </revision>
        
        <notes>
          <scm:Note>Added permission scopes to Client configuration
          </scm:Note>
        </notes>

        <path>source/spiralcraft/linkedin
        </path>
        
        <resources>
          <URI>Client.java
          </URI>
          <URI>Scope.java
          </URI>
          <URI>StandardClient.assy.xml
          </URI>
        </resources>
      </scm:Change>

      <scm:Change>
        <revision>-dev1
        </revision>
        
        <notes>
          <scm:Note>Initial commit
          </scm:Note>
        </notes>

      </scm:Change>

    </detail>
  </scm:Change>
  
</scm:Change.list>